testpkg_sean/__init__.py
testpkg_sean-0.1.4.dist-info/METADATA
testpkg_sean-0.1.4.dist-info/WHEEL
testpkg_sean-0.1.4.dist-info/RECORD
